edwh/__about__.py
edwh/__init__.py
edwh/__main__.py
edwh/cli.py
edwh/constants.py
edwh/discover.py
edwh/health.py
edwh/helpers.py
edwh/meta.py
edwh/py.typed
edwh/tasks.py
edwh/local_tasks/__init__.py
edwh/local_tasks/plugin.py
edwh-1.7.3.dist-info/METADATA
edwh-1.7.3.dist-info/WHEEL
edwh-1.7.3.dist-info/entry_points.txt
edwh-1.7.3.dist-info/RECORD
