Metadata-Version: 2.4
Name: edwh
Version: 1.7.3
Summary: Education Warehouse maintenance tools
Project-URL: Documentation, https://github.com/educationwarehouse/edwh#readme
Project-URL: Issues, https://github.com/educationwarehouse/edwh/issues
Project-URL: Source, https://github.com/educationwarehouse/edwh
Author-email: Remco Boerma <remco.b@educationwarehouse.nl>, Robin van der Noord <robin.vdn@educationwarehouse.nl>, Romy Schöller <romy.s@educationwarehouse.nl>, Sven Keimpema <sven.k@educationwarehouse.nl>
Classifier: Development Status :: 4 - Beta
Classifier: Programming Language :: Python
Classifier: Programming Language :: Python :: 3.12
Classifier: Programming Language :: Python :: 3.13
Classifier: Programming Language :: Python :: Implementation :: CPython
Classifier: Programming Language :: Python :: Implementation :: PyPy
Requires-Python: >=3.12
Requires-Dist: anyio<5
Requires-Dist: click<9
Requires-Dist: diceware<2
Requires-Dist: docstring-parser<1
Requires-Dist: ewok<2,>=0.4.5
Requires-Dist: humanize<5
Requires-Dist: keyring<26
Requires-Dist: more-itertools<11
Requires-Dist: packaging<25
Requires-Dist: plumbum<2
Requires-Dist: python-dateutil<3
Requires-Dist: python-dotenv<2
Requires-Dist: pyyaml<7
Requires-Dist: rapidfuzz<4
Requires-Dist: requests<3
Requires-Dist: ruff==0.14.9
Requires-Dist: tabulate<1
Requires-Dist: termcolor<3
Requires-Dist: threadful<1,>=0.5
Requires-Dist: tomlkit<1
Requires-Dist: tqdm<5
Requires-Dist: typing-extensions<5
Requires-Dist: uv<1
Requires-Dist: yayarl<3
Provides-Extra: b2
Requires-Dist: edwh-b2-plugin; extra == 'b2'
Provides-Extra: bundle
Requires-Dist: edwh-bundler-plugin; extra == 'bundle'
Provides-Extra: bundler
Requires-Dist: edwh-bundler-plugin; extra == 'bundler'
Provides-Extra: dev
Requires-Dist: hatch; extra == 'dev'
Requires-Dist: python-semantic-release<8; extra == 'dev'
Requires-Dist: types-python-dateutil; extra == 'dev'
Requires-Dist: types-redis; extra == 'dev'
Requires-Dist: types-requests; extra == 'dev'
Requires-Dist: types-tabulate; extra == 'dev'
Provides-Extra: devdb
Requires-Dist: edwh-devdb-plugin; extra == 'devdb'
Provides-Extra: files
Requires-Dist: edwh-files-plugin; extra == 'files'
Provides-Extra: git
Requires-Dist: edwh-git-plugin; extra == 'git'
Provides-Extra: locust
Requires-Dist: edwh-locust-plugin; extra == 'locust'
Provides-Extra: multipass
Requires-Dist: edwh-multipass-plugin; extra == 'multipass'
Provides-Extra: omgeving
Provides-Extra: pip
Requires-Dist: edwh-pipcompile-plugin; extra == 'pip'
Provides-Extra: pip-compile
Requires-Dist: edwh-pipcompile-plugin; extra == 'pip-compile'
Provides-Extra: plugins
Requires-Dist: edwh-b2-plugin; extra == 'plugins'
Requires-Dist: edwh-bundler-plugin; extra == 'plugins'
Requires-Dist: edwh-demo-plugin; extra == 'plugins'
Requires-Dist: edwh-devdb-plugin; extra == 'plugins'
Requires-Dist: edwh-files-plugin; extra == 'plugins'
Requires-Dist: edwh-git-plugin; extra == 'plugins'
Requires-Dist: edwh-locust-plugin; extra == 'plugins'
Requires-Dist: edwh-multipass-plugin; extra == 'plugins'
Requires-Dist: edwh-pipcompile-plugin; extra == 'plugins'
Requires-Dist: edwh-restic-plugin; extra == 'plugins'
Requires-Dist: edwh-server-provisioning-plugin; extra == 'plugins'
Requires-Dist: edwh-sshfs-plugin; extra == 'plugins'
Requires-Dist: edwh-sshkey-plugin; extra == 'plugins'
Requires-Dist: edwh-uptime-plugin; extra == 'plugins'
Requires-Dist: edwh-whitelabel-plugin; extra == 'plugins'
Provides-Extra: restic
Requires-Dist: edwh-restic-plugin; extra == 'restic'
Provides-Extra: server-plugins
Requires-Dist: edwh-b2-plugin; extra == 'server-plugins'
Requires-Dist: edwh-bundler-plugin; extra == 'server-plugins'
Requires-Dist: edwh-devdb-plugin; extra == 'server-plugins'
Requires-Dist: edwh-files-plugin; extra == 'server-plugins'
Requires-Dist: edwh-pipcompile-plugin; extra == 'server-plugins'
Requires-Dist: edwh-restic-plugin; extra == 'server-plugins'
Requires-Dist: edwh-uptime-plugin; extra == 'server-plugins'
Provides-Extra: server-provisioning
Requires-Dist: edwh-server-provisioning-plugin; extra == 'server-provisioning'
Provides-Extra: sshfs
Requires-Dist: edwh-sshfs-plugin; extra == 'sshfs'
Provides-Extra: sshkey
Requires-Dist: edwh-sshkey-plugin; extra == 'sshkey'
Provides-Extra: uptime
Requires-Dist: edwh-uptime-plugin; extra == 'uptime'
Provides-Extra: whitelabel
Requires-Dist: edwh-whitelabel-plugin; extra == 'whitelabel'
